mynewlib1/__init__.py
mynewlib1/math/__init__.py
mynewlib1/math/operations.py
mynewlib1/str_op/__init__.py
mynewlib1/str_op/strop.py
mynewlib1-1.0.25.dist-info/METADATA
mynewlib1-1.0.25.dist-info/WHEEL
mynewlib1-1.0.25.dist-info/top_level.txt
mynewlib1-1.0.25.dist-info/RECORD
