Metadata-Version: 2.1
Name: mynewlib1
Version: 1.0.25
Summary: Библиотека для работы с факториалами и вычисления чисел из формул типа str
Home-page: https://github.com/Anromit/mylib/tree/main/mylib
Author: Romitsina Spelov
Author-email: romitsina.a.r@gmail.com
License: example
Classifier: Programming Language :: Python :: 3
Classifier: Operating System :: OS Independent
Requires-Python: >=3.12
